grphpkg/__init__.py
grphpkg/graph.py
grphpkg/weighted_graph.py
grphpkg-0.0.4.dist-info/LICENSE
grphpkg-0.0.4.dist-info/METADATA
grphpkg-0.0.4.dist-info/WHEEL
grphpkg-0.0.4.dist-info/top_level.txt
grphpkg-0.0.4.dist-info/RECORD
