Metadata-Version: 2.1
Name: grphpkg
Version: 0.0.4
Summary: Graph package
Home-page: https://github.com/vudiep411/grphpkg
Author: Vu Diep
Author-email: vudiep411@gmail.com
Keywords: python,data structure,graph,visualization
License-File: LICENSE
Requires-Dist: networkx
Requires-Dist: matplotlib
